CHANGES.rst
LICENSE.txt
MANIFEST.in
README.rst
TODO.txt
setup.py
examples/hook_button.py
examples/mute_led.py
examples/pnp_qt.py
examples/pnp_sample.py
examples/raw_data.py
examples/raw_set.py
examples/show_hids.py
examples/simple_feature.py
examples/simple_send.py
felipe/datosusb.txt
py25/Lib/no-global-site-packages.txt
py25/Lib/orig-prefix.txt
py25/Lib/site-packages/pip-1.2.1-py2.5.egg/EGG-INFO/SOURCES.txt
py25/Lib/site-packages/pip-1.2.1-py2.5.egg/EGG-INFO/dependency_links.txt
py25/Lib/site-packages/pip-1.2.1-py2.5.egg/EGG-INFO/entry_points.txt
py25/Lib/site-packages/pip-1.2.1-py2.5.egg/EGG-INFO/top_level.txt
py26/Lib/no-global-site-packages.txt
py26/Lib/orig-prefix.txt
py26/Lib/site-packages/pip-1.2.1-py2.6.egg/EGG-INFO/SOURCES.txt
py26/Lib/site-packages/pip-1.2.1-py2.6.egg/EGG-INFO/dependency_links.txt
py26/Lib/site-packages/pip-1.2.1-py2.6.egg/EGG-INFO/entry_points.txt
py26/Lib/site-packages/pip-1.2.1-py2.6.egg/EGG-INFO/top_level.txt
py27/Lib/no-global-site-packages.txt
py27/Lib/orig-prefix.txt
py33/Lib/no-global-site-packages.txt
py33/Lib/orig-prefix.txt
py33/Lib/site-packages/distribute-0.6.28-py3.3.egg/EGG-INFO/SOURCES.txt
py33/Lib/site-packages/distribute-0.6.28-py3.3.egg/EGG-INFO/dependency_links.txt
py33/Lib/site-packages/distribute-0.6.28-py3.3.egg/EGG-INFO/entry_points.txt
py33/Lib/site-packages/distribute-0.6.28-py3.3.egg/EGG-INFO/top_level.txt
py33/Lib/site-packages/pip-1.2.1-py3.3.egg/EGG-INFO/SOURCES.txt
py33/Lib/site-packages/pip-1.2.1-py3.3.egg/EGG-INFO/dependency_links.txt
py33/Lib/site-packages/pip-1.2.1-py3.3.egg/EGG-INFO/entry_points.txt
py33/Lib/site-packages/pip-1.2.1-py3.3.egg/EGG-INFO/top_level.txt
pywinusb/__init__.py
pywinusb.egg-info/PKG-INFO
pywinusb.egg-info/SOURCES.txt
pywinusb.egg-info/dependency_links.txt
pywinusb.egg-info/namespace_packages.txt
pywinusb.egg-info/top_level.txt
pywinusb/browse/todo.txt
pywinusb/hid/__init__.py
pywinusb/hid/core.py
pywinusb/hid/helpers.py
pywinusb/hid/hid_pnp_mixin.py
pywinusb/hid/tools.py
pywinusb/hid/usage_pages.py
pywinusb/hid/winapi.py
pywinusb/hid/wnd_hook_mixin.py