Metadata-Version: 1.1
Name: pywinusb
Version: 0.4.0
Summary: A package that simplifies USB/HID communications on windows
Home-page: https://github.com/rene-aguirre/pywinusb
Author: Rene F. Aguirre
Author-email: rene.f.aguirre@gmail.com
License: BSD
Keywords: hid usb usages
Platform: UNKNOWN
Classifier: Development Status :: 5 - Production/Stable
Classifier: Environment :: Win32 (MS Windows)
Classifier: Operating System :: Microsoft :: Windows
Classifier: Programming Language :: Python :: 2.7
Classifier: Programming Language :: Python :: 3.3
Classifier: License :: OSI Approved :: BSD License
Classifier: Topic :: System :: Hardware
Classifier: Topic :: System :: Hardware :: Hardware Drivers
Classifier: Topic :: Scientific/Engineering :: Human Machine Interfaces
Classifier: Topic :: Software Development :: Embedded Systems
Classifier: Topic :: Software Development :: Libraries
Classifier: Topic :: Software Development :: Libraries :: Python Modules
Classifier: Topic :: Utilities
Classifier: Intended Audience :: Developers
